pySimple/__init__.py
pySimple/pyChat.py
MakeItSimplerJKX-0.0.4.dist-info/METADATA
MakeItSimplerJKX-0.0.4.dist-info/WHEEL
MakeItSimplerJKX-0.0.4.dist-info/top_level.txt
MakeItSimplerJKX-0.0.4.dist-info/RECORD
